trs_interface/__init__.py
trs_interface/protocol/__init__.py
trs_interface/protocol/_protocol_h_to_py.py
trs_interface/protocol/decoder.py
trs_interface/protocol/encoder.py
trs_interface-1.4.3.dist-info/LICENSE
trs_interface-1.4.3.dist-info/METADATA
trs_interface-1.4.3.dist-info/WHEEL
trs_interface-1.4.3.dist-info/top_level.txt
trs_interface-1.4.3.dist-info/RECORD
