Metadata-Version: 2.1
Name: trs-interface
Version: 1.4.3
Summary: Library for communicating with the TRSpectrometer interface device.
Home-page: https://gitlab.com/ptapping/trs-interface
Author: Patrick Tapping
Author-email: mail@patricktapping.com
License: UNKNOWN
Project-URL: Documentation, https://trs-interface.readthedocs.io/
Project-URL: Source, https://gitlab.com/ptapping/trs-interface
Project-URL: Tracker, https://gitlab.com/ptapping/trs-interface/-/issues
Platform: UNKNOWN
Classifier: Programming Language :: Python :: 3
Classifier: License :: OSI Approved :: GNU General Public License v3 or later (GPLv3+)
Classifier: Operating System :: OS Independent
Requires-Python: >=3.6
License-File: LICENSE
Requires-Dist: numpy
Requires-Dist: pyserial
